osjsonrpc/__init__.py
osjsonrpc/jsonrpc.py
osjsonrpc-0.2.3.dist-info/LICENSE
osjsonrpc-0.2.3.dist-info/WHEEL
osjsonrpc-0.2.3.dist-info/METADATA
osjsonrpc-0.2.3.dist-info/RECORD
