Metadata-Version: 2.1
Name: osjsonrpc
Version: 0.2.3
Summary: Over-simple JSON-RPC Python implementation for aiohttp
Home-page: https://github.com/k-vinogradov/osjsonrpc
License: MIT
Keywords: jsonrpc,api,rpc
Author: Konstantin V.
Author-email: mail@k-vinogradov.ru
Requires-Python: >=3.6,<4.0
Classifier: License :: OSI Approved :: MIT License
Classifier: Programming Language :: Python :: 3
Classifier: Programming Language :: Python :: 3.6
Classifier: Programming Language :: Python :: 3.7
Classifier: Programming Language :: Python :: 3.8
Requires-Dist: aiohttp (>=3.6.2,<4.0.0)
Project-URL: Repository, https://github.com/k-vinogradov/osjsonrpc
